profab/__init__.py
profab/import_dataset/__init__.py
profab/import_dataset/data_importer.py
profab/import_dataset/data_loader.py
profab/model_evaluate/__init__.py
profab/model_evaluate/evaluation_metrics.py
profab/model_evaluate/form_table.py
profab/model_learn/__init__.py
profab/model_learn/classifications.py
profab/model_learn/hyperparameters.py
profab/model_learn/regressions.py
profab/model_preprocess/__init__.py
profab/model_preprocess/extracter.py
profab/model_preprocess/scaler.py
profab/model_preprocess/splitter.py
profab/utils/__init__.py
profab/utils/imp_split_form.py
profab/utils/feature_extraction_module/__init__.py
profab/utils/feature_extraction_module/feature_extracter.py
profab/utils/feature_extraction_module/utils.py
profab/utils/feature_extraction_module/POSSUM_Standalone_Toolkit/__init__.py
profab/utils/feature_extraction_module/POSSUM_Standalone_Toolkit/src/__init__.py
profab/utils/feature_extraction_module/POSSUM_Standalone_Toolkit/src/featureGenerator.py
profab/utils/feature_extraction_module/POSSUM_Standalone_Toolkit/src/headerHandler.py
profab/utils/feature_extraction_module/POSSUM_Standalone_Toolkit/src/matrixTransformer.py
profab/utils/feature_extraction_module/POSSUM_Standalone_Toolkit/src/possum.py
profab/utils/feature_extraction_module/POSSUM_Standalone_Toolkit/src/possum_ft.py
profab/utils/feature_extraction_module/iFeature/__init__.py
profab/utils/feature_extraction_module/iFeature/cluster.py
profab/utils/feature_extraction_module/iFeature/feaSelector.py
profab/utils/feature_extraction_module/iFeature/iFeature.py
profab/utils/feature_extraction_module/iFeature/iFeaturePseKRAAC.py
profab/utils/feature_extraction_module/iFeature/PseKRAAC/__init__.py
profab/utils/feature_extraction_module/iFeature/PseKRAAC/type1.py
profab/utils/feature_extraction_module/iFeature/PseKRAAC/type10.py
profab/utils/feature_extraction_module/iFeature/PseKRAAC/type11.py
profab/utils/feature_extraction_module/iFeature/PseKRAAC/type12.py
profab_pypi-1.0.dist-info/LICENSE
profab_pypi-1.0.dist-info/METADATA
profab_pypi-1.0.dist-info/WHEEL
profab_pypi-1.0.dist-info/top_level.txt
profab_pypi-1.0.dist-info/RECORD
