Metadata-Version: 2.1
Name: profab-pypi
Version: 1.0
Summary: Installation of Package
Home-page: https://github.com/Sametle06/ProFAB
Author: samet ozdilek
Author-email: oz.samet.473@gmail.com
Project-URL: Bug Tracker, https://github.com/Sametle06/ProFAB/issues
Classifier: Programming Language :: Python :: 3
Classifier: License :: OSI Approved :: MIT License
Requires-Python: >=3.7
License-File: LICENSE
Requires-Dist: wget (==3.2)
Requires-Dist: tqdm (==4.63.0)
Requires-Dist: requests (==2.27.1)
Requires-Dist: numpy (==1.21.2)
Requires-Dist: scikit-learn (==1.0.1)
